LICENSE.txt
MANIFEST.in
README.rst
bootstrap.py
buildout.cfg
setup.py
xbob/__init__.py
xbob.paper.BIOSIG2014.egg-info/PKG-INFO
xbob.paper.BIOSIG2014.egg-info/SOURCES.txt
xbob.paper.BIOSIG2014.egg-info/dependency_links.txt
xbob.paper.BIOSIG2014.egg-info/entry_points.txt
xbob.paper.BIOSIG2014.egg-info/namespace_packages.txt
xbob.paper.BIOSIG2014.egg-info/requires.txt
xbob.paper.BIOSIG2014.egg-info/top_level.txt
xbob/paper/__init__.py
xbob/paper/BIOSIG2014/__init__.py
xbob/paper/BIOSIG2014/evaluate.py
xbob/paper/BIOSIG2014/execute.py