Metadata-Version: 1.1
Name: xbob.paper.BIOSIG2014
Version: 1.0.0
Summary: Running the experiments as given in paper: "On the Vulnerability of Finger Vein Recognition to Spoofing".
Home-page: http://gitlab.idiap.ch/pedro.tome/xbob.paper.biosig2014
Author: Pedro Tome
Author-email: pedro.tome@idiap.ch
License: LICENSE.txt
Platform: UNKNOWN
Classifier: Development Status :: 4 - Beta
Classifier: Intended Audience :: Science/Research
Classifier: License :: OSI Approved :: GNU General Public License v3 (GPLv3)
Classifier: Natural Language :: English
Classifier: Programming Language :: Python :: 2.7
Classifier: Environment :: Console
Classifier: Framework :: Buildout
Classifier: Topic :: Scientific/Engineering
